[[{"date": "2014-02-24T19:00:00+04:00", "team1": "philadelphia-76ers", "team2": "milwaukee-bucks"}, {"date": "2014-02-24T19:30:00+04:00", "team1": "new-york-knicks", "team2": "dallas-mavericks"}, {"date": "2014-02-24T19:30:00+04:00", "team1": "detroit-pistons", "team2": "golden-state-warriors"}, {"date": "2014-02-24T20:00:00+04:00", "team1": "new-orleans-pelicans", "team2": "los-angeles-clippers"}, {"date": "2014-02-24T21:00:00+04:00", "team1": "utah-jazz", "team2": "boston-celtics"}], [{"date": "2014-02-25T19:00:00+04:00", "team1": "washington-wizards", "team2": "orlando_magic"}, {"date": "2014-02-25T19:00:00+04:00", "team1": "cleveland-cavaliers", "team2": "toronto-raptors"}, {"date": "2014-02-25T19:00:00+04:00", "team1": "indiana-pacers", "team2": "los-angeles-lakers"}, {"date": "2014-02-25T19:30:00+04:00", "team1": "atlanta-hawks", "team2": "chicago-bulls"}, {"date": "2014-02-25T21:00:00+04:00", "team1": "phoenix-suns", "team2": "minnesota-timberwolves"}, {"date": "2014-02-25T21:00:00+04:00", "team1": "denver-nuggets", "team2": "portland-trail-blazers"}, {"date": "2014-02-25T22:00:00+04:00", "team1": "sacramento-kings", "team2": "houston-rockets"}], [{"date": "2014-02-26T19:00:00+04:00", "team1": "philadelphia-76ers", "team2": "orlando_magic"}, {"date": "2014-02-26T19:30:00+04:00", "team1": "boston-celtics", "team2": "atlanta-hawks"}, {"date": "2014-02-26T20:00:00+04:00", "team1": "memphis-grizzlies", "team2": "los-angeles-lakers"}, {"date": "2014-02-26T20:00:00+04:00", "team1": "chicago-bulls", "team2": "golden-state-warriors"}, {"date": "2014-02-26T20:00:00+04:00", "team1": "oklahoma-city-thunder", "team2": "cleveland-cavaliers"}, {"date": "2014-02-26T20:00:00+04:00", "team1": "dallas-mavericks", "team2": "new-orleans-pelicans"}, {"date": "2014-02-26T20:30:00+04:00", "team1": "san-antonio-spurs", "team2": "detroit-pistons"}, {"date": "2014-02-26T21:00:00+04:00", "team1": "utah-jazz", "team2": "phoenix-suns"}, {"date": "2014-02-26T22:00:00+04:00", "team1": "portland-trail-blazers", "team2": "brooklyn-nets"}, {"date": "2014-02-26T22:30:00+04:00", "team1": "los-angeles-clippers", "team2": "houston-rockets"}], [{"date": "2014-02-27T19:00:00+04:00", "team1": "toronto-raptors", "team2": "washington-wizards"}, {"date": "2014-02-27T19:00:00+04:00", "team1": "indiana-pacers", "team2": "milwaukee-bucks"}, {"date": "2014-02-27T20:00:00+04:00", "team1": "miami-heat", "team2": "new-york-knicks"}, {"date": "2014-02-27T22:30:00+04:00", "team1": "denver-nuggets", "team2": "brooklyn-nets"}], [{"date": "2014-02-28T19:30:00+04:00", "team1": "cleveland-cavaliers", "team2": "utah-jazz"}, {"date": "2014-02-28T20:00:00+04:00", "team1": "oklahoma-city-thunder", "team2": "memphis-grizzlies"}, {"date": "2014-02-28T20:00:00+04:00", "team1": "new-york-knicks", "team2": "golden-state-warriors"}, {"date": "2014-02-28T20:30:00+04:00", "team1": "dallas-mavericks", "team2": "chicago-bulls"}, {"date": "2014-02-28T20:30:00+04:00", "team1": "san-antonio-spurs", "team2": "charlotte-bobcats"}, {"date": "2014-02-28T22:30:00+04:00", "team1": "phoenix-suns", "team2": "new-orleans-pelicans"}, {"date": "2014-02-28T22:30:00+04:00", "team1": "los-angeles-lakers", "team2": "sacramento-kings"}], [{"date": "2014-03-01T19:30:00+04:00", "team1": "miami-heat", "team2": "orlando_magic"}, {"date": "2014-03-01T19:30:00+04:00", "team1": "philadelphia-76ers", "team2": "washington-wizards"}, {"date": "2014-03-01T20:00:00+04:00", "team1": "houston-rockets", "team2": "detroit-pistons"}, {"date": "2014-03-01T20:00:00+04:00", "team1": "boston-celtics", "team2": "indiana-pacers"}, {"date": "2014-03-01T20:30:00+04:00", "team1": "milwaukee-bucks", "team2": "brooklyn-nets"}, {"date": "2014-03-01T21:00:00+04:00", "team1": "memphis-grizzlies", "team2": "cleveland-cavaliers"}, {"date": "2014-03-01T22:00:00+04:00", "team1": "sacramento-kings", "team2": "minnesota-timberwolves"}, {"date": "2014-03-01T22:00:00+04:00", "team1": "portland-trail-blazers", "team2": "denver-nuggets"}, {"date": "2014-03-01T22:30:00+04:00", "team1": "los-angeles-clippers", "team2": "new-orleans-pelicans"}], [{"date": "2014-03-02T13:00:00+04:00", "team1": "chicago-bulls", "team2": "new-york-knicks"}, {"date": "2014-03-02T16:00:00+04:00", "team1": "toronto-raptors", "team2": "golden-state-warriors"}, {"date": "2014-03-02T18:00:00+04:00", "team1": "orlando_magic", "team2": "philadelphia-76ers"}, {"date": "2014-03-02T18:00:00+04:00", "team1": "indiana-pacers", "team2": "utah-jazz"}, {"date": "2014-03-02T19:00:00+04:00", "team1": "oklahoma-city-thunder", "team2": "charlotte-bobcats"}, {"date": "2014-03-02T19:00:00+04:00", "team1": "san-antonio-spurs", "team2": "dallas-mavericks"}, {"date": "2014-03-02T20:00:00+04:00", "team1": "phoenix-suns", "team2": "atlanta-hawks"}], [{"date": "2014-03-03T19:00:00+04:00", "team1": "washington-wizards", "team2": "memphis-grizzlies"}, {"date": "2014-03-03T19:30:00+04:00", "team1": "detroit-pistons", "team2": "new-york-knicks"}, {"date": "2014-03-03T19:30:00+04:00", "team1": "miami-heat", "team2": "charlotte-bobcats"}, {"date": "2014-03-03T19:30:00+04:00", "team1": "brooklyn-nets", "team2": "chicago-bulls"}, {"date": "2014-03-03T20:00:00+04:00", "team1": "milwaukee-bucks", "team2": "utah-jazz"}, {"date": "2014-03-03T21:00:00+04:00", "team1": "denver-nuggets", "team2": "minnesota-timberwolves"}, {"date": "2014-03-03T22:00:00+04:00", "team1": "portland-trail-blazers", "team2": "los-angeles-lakers"}, {"date": "2014-03-03T22:00:00+04:00", "team1": "sacramento-kings", "team2": "new-orleans-pelicans"}], [{"date": "2014-03-04T19:00:00+04:00", "team1": "indiana-pacers", "team2": "golden-state-warriors"}, {"date": "2014-03-04T19:00:00+04:00", "team1": "cleveland-cavaliers", "team2": "san-antonio-spurs"}, {"date": "2014-03-04T20:00:00+04:00", "team1": "houston-rockets", "team2": "miami-heat"}, {"date": "2014-03-04T20:00:00+04:00", "team1": "oklahoma-city-thunder", "team2": "philadelphia-76ers"}, {"date": "2014-03-04T21:00:00+04:00", "team1": "phoenix-suns", "team2": "los-angeles-clippers"}, {"date": "2014-03-04T22:30:00+04:00", "team1": "los-angeles-lakers", "team2": "new-orleans-pelicans"}], [{"date": "2014-03-05T19:00:00+04:00", "team1": "charlotte-bobcats", "team2": "indiana-pacers"}, {"date": "2014-03-05T19:00:00+04:00", "team1": "orlando_magic", "team2": "houston-rockets"}, {"date": "2014-03-05T19:00:00+04:00", "team1": "washington-wizards", "team2": "utah-jazz"}, {"date": "2014-03-05T19:30:00+04:00", "team1": "detroit-pistons", "team2": "chicago-bulls"}, {"date": "2014-03-05T19:30:00+04:00", "team1": "boston-celtics", "team2": "golden-state-warriors"}, {"date": "2014-03-05T19:30:00+04:00", "team1": "brooklyn-nets", "team2": "memphis-grizzlies"}, {"date": "2014-03-05T20:00:00+04:00", "team1": "minnesota-timberwolves", "team2": "new-york-knicks"}, {"date": "2014-03-05T20:00:00+04:00", "team1": "milwaukee-bucks", "team2": "sacramento-kings"}, {"date": "2014-03-05T21:00:00+04:00", "team1": "denver-nuggets", "team2": "dallas-mavericks"}, {"date": "2014-03-05T22:30:00+04:00", "team1": "portland-trail-blazers", "team2": "atlanta-hawks"}], [{"date": "2014-03-06T20:00:00+04:00", "team1": "san-antonio-spurs", "team2": "miami-heat"}, {"date": "2014-03-06T21:00:00+04:00", "team1": "phoenix-suns", "team2": "oklahoma-city-thunder"}, {"date": "2014-03-06T22:30:00+04:00", "team1": "los-angeles-lakers", "team2": "los-angeles-clippers"}], [{"date": "2014-03-07T19:00:00+04:00", "team1": "chicago-bulls", "team2": "memphis-grizzlies"}, {"date": "2014-03-07T19:00:00+04:00", "team1": "toronto-raptors", "team2": "sacramento-kings"}, {"date": "2014-03-07T19:00:00+04:00", "team1": "charlotte-bobcats", "team2": "cleveland-cavaliers"}, {"date": "2014-03-07T19:30:00+04:00", "team1": "new-york-knicks", "team2": "utah-jazz"}, {"date": "2014-03-07T19:30:00+04:00", "team1": "boston-celtics", "team2": "brooklyn-nets"}, {"date": "2014-03-07T20:00:00+04:00", "team1": "new-orleans-pelicans", "team2": "milwaukee-bucks"}, {"date": "2014-03-07T20:00:00+04:00", "team1": "minnesota-timberwolves", "team2": "detroit-pistons"}, {"date": "2014-03-07T20:30:00+04:00", "team1": "dallas-mavericks", "team2": "portland-trail-blazers"}, {"date": "2014-03-07T21:00:00+04:00", "team1": "denver-nuggets", "team2": "los-angeles-lakers"}, {"date": "2014-03-07T21:30:00+04:00", "team1": "houston-rockets", "team2": "indiana-pacers"}, {"date": "2014-03-07T22:30:00+04:00", "team1": "golden-state-warriors", "team2": "atlanta-hawks"}], [{"date": "2014-03-08T19:30:00+04:00", "team1": "cleveland-cavaliers", "team2": "new-york-knicks"}, {"date": "2014-03-08T19:30:00+04:00", "team1": "philadelphia-76ers", "team2": "utah-jazz"}, {"date": "2014-03-08T20:00:00+04:00", "team1": "memphis-grizzlies", "team2": "charlotte-bobcats"}, {"date": "2014-03-08T20:30:00+04:00", "team1": "san-antonio-spurs", "team2": "orlando_magic"}, {"date": "2014-03-08T20:30:00+04:00", "team1": "milwaukee-bucks", "team2": "washington-wizards"}, {"date": "2014-03-08T22:30:00+04:00", "team1": "los-angeles-clippers", "team2": "atlanta-hawks"}], [{"date": "2014-03-09T13:00:00+04:00", "team1": "chicago-bulls", "team2": "miami-heat"}, {"date": "2014-03-09T15:30:00+04:00", "team1": "los-angeles-lakers", "team2": "oklahoma-city-thunder"}, {"date": "2014-03-09T18:00:00+04:00", "team1": "boston-celtics", "team2": "detroit-pistons"}, {"date": "2014-03-09T18:00:00+04:00", "team1": "brooklyn-nets", "team2": "sacramento-kings"}, {"date": "2014-03-09T18:00:00+04:00", "team1": "new-orleans-pelicans", "team2": "denver-nuggets"}, {"date": "2014-03-09T19:00:00+04:00", "team1": "minnesota-timberwolves", "team2": "toronto-raptors"}, {"date": "2014-03-09T19:00:00+04:00", "team1": "houston-rockets", "team2": "portland-trail-blazers"}, {"date": "2014-03-09T19:30:00+04:00", "team1": "dallas-mavericks", "team2": "indiana-pacers"}, {"date": "2014-03-09T21:00:00+04:00", "team1": "golden-state-warriors", "team2": "phoenix-suns"}], [{"date": "2014-03-10T19:00:00+04:00", "team1": "charlotte-bobcats", "team2": "denver-nuggets"}, {"date": "2014-03-10T19:30:00+04:00", "team1": "miami-heat", "team2": "washington-wizards"}, {"date": "2014-03-10T19:30:00+04:00", "team1": "new-york-knicks", "team2": "philadelphia-76ers"}, {"date": "2014-03-10T19:30:00+04:00", "team1": "brooklyn-nets", "team2": "toronto-raptors"}, {"date": "2014-03-10T20:00:00+04:00", "team1": "milwaukee-bucks", "team2": "orlando_magic"}, {"date": "2014-03-10T21:00:00+04:00", "team1": "utah-jazz", "team2": "atlanta-hawks"}, {"date": "2014-03-10T22:30:00+04:00", "team1": "los-angeles-clippers", "team2": "phoenix-suns"}], [{"date": "2014-03-11T19:00:00+04:00", "team1": "indiana-pacers", "team2": "boston-celtics"}, {"date": "2014-03-11T19:30:00+04:00", "team1": "detroit-pistons", "team2": "sacramento-kings"}, {"date": "2014-03-11T20:00:00+04:00", "team1": "memphis-grizzlies", "team2": "portland-trail-blazers"}, {"date": "2014-03-11T20:00:00+04:00", "team1": "oklahoma-city-thunder", "team2": "houston-rockets"}, {"date": "2014-03-11T20:00:00+04:00", "team1": "minnesota-timberwolves", "team2": "milwaukee-bucks"}, {"date": "2014-03-11T20:00:00+04:00", "team1": "chicago-bulls", "team2": "san-antonio-spurs"}, {"date": "2014-03-11T22:30:00+04:00", "team1": "golden-state-warriors", "team2": "dallas-mavericks"}], [{"date": "2014-03-12T19:00:00+04:00", "team1": "toronto-raptors", "team2": "detroit-pistons"}, {"date": "2014-03-12T19:00:00+04:00", "team1": "miami-heat", "team2": "brooklyn-nets"}, {"date": "2014-03-12T19:00:00+04:00", "team1": "orlando_magic", "team2": "denver-nuggets"}, {"date": "2014-03-12T19:00:00+04:00", "team1": "philadelphia-76ers", "team2": "sacramento-kings"}, {"date": "2014-03-12T19:00:00+04:00", "team1": "washington-wizards", "team2": "charlotte-bobcats"}, {"date": "2014-03-12T19:30:00+04:00", "team1": "boston-celtics", "team2": "new-york-knicks"}, {"date": "2014-03-12T20:00:00+04:00", "team1": "new-orleans-pelicans", "team2": "memphis-grizzlies"}, {"date": "2014-03-12T21:00:00+04:00", "team1": "utah-jazz", "team2": "dallas-mavericks"}, {"date": "2014-03-12T21:30:00+04:00", "team1": "san-antonio-spurs", "team2": "portland-trail-blazers"}, {"date": "2014-03-12T22:00:00+04:00", "team1": "phoenix-suns", "team2": "cleveland-cavaliers"}, {"date": "2014-03-12T22:30:00+04:00", "team1": "los-angeles-clippers", "team2": "golden-state-warriors"}], [{"date": "2014-03-13T19:00:00+04:00", "team1": "chicago-bulls", "team2": "houston-rockets"}, {"date": "2014-03-13T19:30:00+04:00", "team1": "atlanta-hawks", "team2": "milwaukee-bucks"}, {"date": "2014-03-13T21:30:00+04:00", "team1": "oklahoma-city-thunder", "team2": "los-angeles-lakers"}], [{"date": "2014-03-14T19:00:00+04:00", "team1": "philadelphia-76ers", "team2": "indiana-pacers"}, {"date": "2014-03-14T19:00:00+04:00", "team1": "toronto-raptors", "team2": "memphis-grizzlies"}, {"date": "2014-03-14T19:00:00+04:00", "team1": "charlotte-bobcats", "team2": "minnesota-timberwolves"}, {"date": "2014-03-14T19:00:00+04:00", "team1": "orlando_magic", "team2": "washington-wizards"}, {"date": "2014-03-14T19:30:00+04:00", "team1": "boston-celtics", "team2": "phoenix-suns"}, {"date": "2014-03-14T19:30:00+04:00", "team1": "miami-heat", "team2": "denver-nuggets"}, {"date": "2014-03-14T20:00:00+04:00", "team1": "new-orleans-pelicans", "team2": "portland-trail-blazers"}, {"date": "2014-03-14T20:30:00+04:00", "team1": "san-antonio-spurs", "team2": "los-angeles-lakers"}, {"date": "2014-03-14T21:00:00+04:00", "team1": "utah-jazz", "team2": "los-angeles-clippers"}, {"date": "2014-03-14T22:30:00+04:00", "team1": "golden-state-warriors", "team2": "cleveland-cavaliers"}], [{"date": "2014-03-15T12:00:00+04:00", "team1": "new-york-knicks", "team2": "milwaukee-bucks"}, {"date": "2014-03-15T19:00:00+04:00", "team1": "washington-wizards", "team2": "brooklyn-nets"}, {"date": "2014-03-15T19:30:00+04:00", "team1": "atlanta-hawks", "team2": "denver-nuggets"}, {"date": "2014-03-15T19:30:00+04:00", "team1": "philadelphia-76ers", "team2": "memphis-grizzlies"}, {"date": "2014-03-15T19:30:00+04:00", "team1": "detroit-pistons", "team2": "indiana-pacers"}, {"date": "2014-03-15T20:00:00+04:00", "team1": "chicago-bulls", "team2": "sacramento-kings"}], [{"date": "2014-03-16T13:00:00+04:00", "team1": "milwaukee-bucks", "team2": "charlotte-bobcats"}, {"date": "2014-03-16T13:00:00+04:00", "team1": "toronto-raptors", "team2": "phoenix-suns"}, {"date": "2014-03-16T15:30:00+04:00", "team1": "miami-heat", "team2": "houston-rockets"}, {"date": "2014-03-16T18:00:00+04:00", "team1": "new-orleans-pelicans", "team2": "boston-celtics"}, {"date": "2014-03-16T19:00:00+04:00", "team1": "san-antonio-spurs", "team2": "utah-jazz"}, {"date": "2014-03-16T19:00:00+04:00", "team1": "minnesota-timberwolves", "team2": "sacramento-kings"}, {"date": "2014-03-16T19:00:00+04:00", "team1": "oklahoma-city-thunder", "team2": "dallas-mavericks"}, {"date": "2014-03-16T21:00:00+04:00", "team1": "portland-trail-blazers", "team2": "golden-state-warriors"}, {"date": "2014-03-16T21:30:00+04:00", "team1": "los-angeles-clippers", "team2": "cleveland-cavaliers"}], [{"date": "2014-03-17T19:00:00+04:00", "team1": "charlotte-bobcats", "team2": "atlanta-hawks"}, {"date": "2014-03-17T19:00:00+04:00", "team1": "indiana-pacers", "team2": "philadelphia-76ers"}, {"date": "2014-03-17T19:30:00+04:00", "team1": "brooklyn-nets", "team2": "phoenix-suns"}, {"date": "2014-03-17T20:00:00+04:00", "team1": "houston-rockets", "team2": "utah-jazz"}, {"date": "2014-03-17T20:00:00+04:00", "team1": "chicago-bulls", "team2": "oklahoma-city-thunder"}, {"date": "2014-03-17T20:30:00+04:00", "team1": "dallas-mavericks", "team2": "boston-celtics"}, {"date": "2014-03-17T22:30:00+04:00", "team1": "denver-nuggets", "team2": "los-angeles-clippers"}], [{"date": "2014-03-18T19:00:00+04:00", "team1": "cleveland-cavaliers", "team2": "miami-heat"}, {"date": "2014-03-18T19:30:00+04:00", "team1": "atlanta-hawks", "team2": "toronto-raptors"}, {"date": "2014-03-18T22:00:00+04:00", "team1": "sacramento-kings", "team2": "washington-wizards"}, {"date": "2014-03-18T22:00:00+04:00", "team1": "portland-trail-blazers", "team2": "milwaukee-bucks"}, {"date": "2014-03-18T22:30:00+04:00", "team1": "golden-state-warriors", "team2": "orlando_magic"}], [{"date": "2014-03-19T19:00:00+04:00", "team1": "philadelphia-76ers", "team2": "chicago-bulls"}, {"date": "2014-03-19T19:30:00+04:00", "team1": "brooklyn-nets", "team2": "charlotte-bobcats"}, {"date": "2014-03-19T19:30:00+04:00", "team1": "boston-celtics", "team2": "miami-heat"}, {"date": "2014-03-19T20:00:00+04:00", "team1": "memphis-grizzlies", "team2": "utah-jazz"}, {"date": "2014-03-19T20:00:00+04:00", "team1": "new-york-knicks", "team2": "indiana-pacers"}, {"date": "2014-03-19T20:00:00+04:00", "team1": "new-orleans-pelicans", "team2": "toronto-raptors"}, {"date": "2014-03-19T20:30:00+04:00", "team1": "dallas-mavericks", "team2": "minnesota-timberwolves"}, {"date": "2014-03-19T21:00:00+04:00", "team1": "denver-nuggets", "team2": "detroit-pistons"}, {"date": "2014-03-19T22:00:00+04:00", "team1": "phoenix-suns", "team2": "orlando_magic"}, {"date": "2014-03-19T22:30:00+04:00", "team1": "los-angeles-lakers", "team2": "san-antonio-spurs"}], [{"date": "2014-03-20T19:00:00+04:00", "team1": "cleveland-cavaliers", "team2": "oklahoma-city-thunder"}, {"date": "2014-03-20T20:00:00+04:00", "team1": "houston-rockets", "team2": "minnesota-timberwolves"}, {"date": "2014-03-20T22:00:00+04:00", "team1": "portland-trail-blazers", "team2": "washington-wizards"}, {"date": "2014-03-20T22:30:00+04:00", "team1": "golden-state-warriors", "team2": "milwaukee-bucks"}], [{"date": "2014-03-21T19:00:00+04:00", "team1": "indiana-pacers", "team2": "chicago-bulls"}, {"date": "2014-03-21T19:00:00+04:00", "team1": "philadelphia-76ers", "team2": "new-york-knicks"}, {"date": "2014-03-21T19:00:00+04:00", "team1": "toronto-raptors", "team2": "oklahoma-city-thunder"}, {"date": "2014-03-21T19:30:00+04:00", "team1": "atlanta-hawks", "team2": "new-orleans-pelicans"}, {"date": "2014-03-21T19:30:00+04:00", "team1": "brooklyn-nets", "team2": "boston-celtics"}, {"date": "2014-03-21T19:30:00+04:00", "team1": "miami-heat", "team2": "memphis-grizzlies"}, {"date": "2014-03-21T20:30:00+04:00", "team1": "dallas-mavericks", "team2": "denver-nuggets"}, {"date": "2014-03-21T22:00:00+04:00", "team1": "phoenix-suns", "team2": "detroit-pistons"}, {"date": "2014-03-21T22:00:00+04:00", "team1": "sacramento-kings", "team2": "san-antonio-spurs"}, {"date": "2014-03-21T22:30:00+04:00", "team1": "los-angeles-lakers", "team2": "washington-wizards"}], [{"date": "2014-03-22T19:00:00+04:00", "team1": "charlotte-bobcats", "team2": "portland-trail-blazers"}, {"date": "2014-03-22T19:30:00+04:00", "team1": "cleveland-cavaliers", "team2": "houston-rockets"}, {"date": "2014-03-22T20:00:00+04:00", "team1": "memphis-grizzlies", "team2": "indiana-pacers"}, {"date": "2014-03-22T20:00:00+04:00", "team1": "new-orleans-pelicans", "team2": "miami-heat"}, {"date": "2014-03-22T20:00:00+04:00", "team1": "chicago-bulls", "team2": "philadelphia-76ers"}, {"date": "2014-03-22T21:00:00+04:00", "team1": "utah-jazz", "team2": "orlando_magic"}, {"date": "2014-03-22T22:30:00+04:00", "team1": "golden-state-warriors", "team2": "san-antonio-spurs"}, {"date": "2014-03-22T22:30:00+04:00", "team1": "los-angeles-clippers", "team2": "detroit-pistons"}], [{"date": "2014-03-23T13:00:00+04:00", "team1": "toronto-raptors", "team2": "atlanta-hawks"}, {"date": "2014-03-23T15:30:00+04:00", "team1": "minnesota-timberwolves", "team2": "phoenix-suns"}, {"date": "2014-03-23T17:00:00+04:00", "team1": "denver-nuggets", "team2": "washington-wizards"}, {"date": "2014-03-23T18:00:00+04:00", "team1": "sacramento-kings", "team2": "milwaukee-bucks"}, {"date": "2014-03-23T19:30:00+04:00", "team1": "new-york-knicks", "team2": "cleveland-cavaliers"}, {"date": "2014-03-23T19:30:00+04:00", "team1": "dallas-mavericks", "team2": "brooklyn-nets"}, {"date": "2014-03-23T21:30:00+04:00", "team1": "los-angeles-lakers", "team2": "orlando_magic"}], [{"date": "2014-03-24T19:00:00+04:00", "team1": "charlotte-bobcats", "team2": "houston-rockets"}, {"date": "2014-03-24T19:30:00+04:00", "team1": "atlanta-hawks", "team2": "phoenix-suns"}, {"date": "2014-03-24T19:30:00+04:00", "team1": "miami-heat", "team2": "portland-trail-blazers"}, {"date": "2014-03-24T20:00:00+04:00", "team1": "chicago-bulls", "team2": "indiana-pacers"}, {"date": "2014-03-24T20:00:00+04:00", "team1": "new-orleans-pelicans", "team2": "brooklyn-nets"}, {"date": "2014-03-24T20:00:00+04:00", "team1": "oklahoma-city-thunder", "team2": "denver-nuggets"}, {"date": "2014-03-24T20:00:00+04:00", "team1": "memphis-grizzlies", "team2": "minnesota-timberwolves"}, {"date": "2014-03-24T20:30:00+04:00", "team1": "san-antonio-spurs", "team2": "philadelphia-76ers"}, {"date": "2014-03-24T21:00:00+04:00", "team1": "utah-jazz", "team2": "detroit-pistons"}, {"date": "2014-03-24T22:30:00+04:00", "team1": "los-angeles-clippers", "team2": "milwaukee-bucks"}], [{"date": "2014-03-25T19:00:00+04:00", "team1": "cleveland-cavaliers", "team2": "toronto-raptors"}, {"date": "2014-03-25T19:00:00+04:00", "team1": "orlando_magic", "team2": "portland-trail-blazers"}, {"date": "2014-03-25T20:00:00+04:00", "team1": "dallas-mavericks", "team2": "oklahoma-city-thunder"}, {"date": "2014-03-25T22:30:00+04:00", "team1": "los-angeles-lakers", "team2": "new-york-knicks"}], [{"date": "2014-03-26T19:00:00+04:00", "team1": "charlotte-bobcats", "team2": "brooklyn-nets"}, {"date": "2014-03-26T19:00:00+04:00", "team1": "washington-wizards", "team2": "phoenix-suns"}, {"date": "2014-03-26T19:30:00+04:00", "team1": "detroit-pistons", "team2": "cleveland-cavaliers"}, {"date": "2014-03-26T19:30:00+04:00", "team1": "boston-celtics", "team2": "toronto-raptors"}, {"date": "2014-03-26T20:00:00+04:00", "team1": "new-orleans-pelicans", "team2": "los-angeles-clippers"}, {"date": "2014-03-26T20:00:00+04:00", "team1": "indiana-pacers", "team2": "miami-heat"}, {"date": "2014-03-26T20:00:00+04:00", "team1": "minnesota-timberwolves", "team2": "atlanta-hawks"}, {"date": "2014-03-26T20:30:00+04:00", "team1": "san-antonio-spurs", "team2": "denver-nuggets"}, {"date": "2014-03-26T22:00:00+04:00", "team1": "sacramento-kings", "team2": "new-york-knicks"}, {"date": "2014-03-26T22:30:00+04:00", "team1": "utah-jazz", "team2": "memphis-grizzlies"}], [{"date": "2014-03-27T19:30:00+04:00", "team1": "atlanta-hawks", "team2": "portland-trail-blazers"}, {"date": "2014-03-27T20:00:00+04:00", "team1": "houston-rockets", "team2": "philadelphia-76ers"}, {"date": "2014-03-27T20:00:00+04:00", "team1": "milwaukee-bucks", "team2": "los-angeles-lakers"}, {"date": "2014-03-27T20:30:00+04:00", "team1": "dallas-mavericks", "team2": "los-angeles-clippers"}], [{"date": "2014-03-28T19:00:00+04:00", "team1": "toronto-raptors", "team2": "boston-celtics"}, {"date": "2014-03-28T19:00:00+04:00", "team1": "washington-wizards", "team2": "indiana-pacers"}, {"date": "2014-03-28T19:00:00+04:00", "team1": "orlando_magic", "team2": "charlotte-bobcats"}, {"date": "2014-03-28T19:30:00+04:00", "team1": "detroit-pistons", "team2": "miami-heat"}, {"date": "2014-03-28T19:30:00+04:00", "team1": "brooklyn-nets", "team2": "cleveland-cavaliers"}, {"date": "2014-03-28T20:00:00+04:00", "team1": "new-orleans-pelicans", "team2": "utah-jazz"}, {"date": "2014-03-28T20:00:00+04:00", "team1": "chicago-bulls", "team2": "portland-trail-blazers"}, {"date": "2014-03-28T20:00:00+04:00", "team1": "minnesota-timberwolves", "team2": "los-angeles-lakers"}, {"date": "2014-03-28T20:00:00+04:00", "team1": "oklahoma-city-thunder", "team2": "sacramento-kings"}, {"date": "2014-03-28T21:00:00+04:00", "team1": "denver-nuggets", "team2": "san-antonio-spurs"}, {"date": "2014-03-28T22:00:00+04:00", "team1": "phoenix-suns", "team2": "new-york-knicks"}, {"date": "2014-03-28T22:30:00+04:00", "team1": "golden-state-warriors", "team2": "memphis-grizzlies"}], [{"date": "2014-03-29T19:30:00+04:00", "team1": "philadelphia-76ers", "team2": "detroit-pistons"}, {"date": "2014-03-29T20:00:00+04:00", "team1": "houston-rockets", "team2": "los-angeles-clippers"}, {"date": "2014-03-29T20:00:00+04:00", "team1": "washington-wizards", "team2": "atlanta-hawks"}, {"date": "2014-03-29T20:30:00+04:00", "team1": "dallas-mavericks", "team2": "sacramento-kings"}, {"date": "2014-03-29T20:30:00+04:00", "team1": "milwaukee-bucks", "team2": "miami-heat"}, {"date": "2014-03-29T20:30:00+04:00", "team1": "san-antonio-spurs", "team2": "new-orleans-pelicans"}], [{"date": "2014-03-30T15:00:00+04:00", "team1": "oklahoma-city-thunder", "team2": "utah-jazz"}, {"date": "2014-03-30T15:00:00+04:00", "team1": "cleveland-cavaliers", "team2": "indiana-pacers"}, {"date": "2014-03-30T18:00:00+04:00", "team1": "brooklyn-nets", "team2": "minnesota-timberwolves"}, {"date": "2014-03-30T18:00:00+04:00", "team1": "orlando_magic", "team2": "toronto-raptors"}, {"date": "2014-03-30T19:00:00+04:00", "team1": "boston-celtics", "team2": "chicago-bulls"}, {"date": "2014-03-30T21:00:00+04:00", "team1": "golden-state-warriors", "team2": "new-york-knicks"}, {"date": "2014-03-30T21:00:00+04:00", "team1": "portland-trail-blazers", "team2": "memphis-grizzlies"}, {"date": "2014-03-30T21:30:00+04:00", "team1": "los-angeles-lakers", "team2": "phoenix-suns"}], [{"date": "2014-03-31T19:00:00+04:00", "team1": "indiana-pacers", "team2": "san-antonio-spurs"}, {"date": "2014-03-31T19:00:00+04:00", "team1": "charlotte-bobcats", "team2": "washington-wizards"}, {"date": "2014-03-31T19:30:00+04:00", "team1": "detroit-pistons", "team2": "milwaukee-bucks"}, {"date": "2014-03-31T19:30:00+04:00", "team1": "atlanta-hawks", "team2": "philadelphia-76ers"}, {"date": "2014-03-31T19:30:00+04:00", "team1": "miami-heat", "team2": "toronto-raptors"}, {"date": "2014-03-31T20:00:00+04:00", "team1": "minnesota-timberwolves", "team2": "los-angeles-clippers"}, {"date": "2014-03-31T20:00:00+04:00", "team1": "new-orleans-pelicans", "team2": "sacramento-kings"}, {"date": "2014-03-31T20:00:00+04:00", "team1": "chicago-bulls", "team2": "boston-celtics"}, {"date": "2014-03-31T21:00:00+04:00", "team1": "denver-nuggets", "team2": "memphis-grizzlies"}, {"date": "2014-03-31T21:00:00+04:00", "team1": "utah-jazz", "team2": "new-york-knicks"}], [{"date": "2014-04-01T20:00:00+04:00", "team1": "brooklyn-nets", "team2": "houston-rockets"}, {"date": "2014-04-01T20:30:00+04:00", "team1": "dallas-mavericks", "team2": "golden-state-warriors"}, {"date": "2014-04-01T22:30:00+04:00", "team1": "los-angeles-lakers", "team2": "portland-trail-blazers"}], [{"date": "2014-04-02T19:00:00+04:00", "team1": "philadelphia-76ers", "team2": "charlotte-bobcats"}, {"date": "2014-04-02T19:00:00+04:00", "team1": "indiana-pacers", "team2": "detroit-pistons"}, {"date": "2014-04-02T19:00:00+04:00", "team1": "new-york-knicks", "team2": "brooklyn-nets"}, {"date": "2014-04-02T19:00:00+04:00", "team1": "toronto-raptors", "team2": "houston-rockets"}, {"date": "2014-04-02T19:00:00+04:00", "team1": "orlando_magic", "team2": "cleveland-cavaliers"}, {"date": "2014-04-02T19:00:00+04:00", "team1": "washington-wizards", "team2": "boston-celtics"}, {"date": "2014-04-02T19:30:00+04:00", "team1": "atlanta-hawks", "team2": "chicago-bulls"}, {"date": "2014-04-02T19:30:00+04:00", "team1": "miami-heat", "team2": "milwaukee-bucks"}, {"date": "2014-04-02T20:00:00+04:00", "team1": "minnesota-timberwolves", "team2": "memphis-grizzlies"}, {"date": "2014-04-02T20:30:00+04:00", "team1": "san-antonio-spurs", "team2": "golden-state-warriors"}, {"date": "2014-04-02T21:00:00+04:00", "team1": "denver-nuggets", "team2": "new-orleans-pelicans"}, {"date": "2014-04-02T22:00:00+04:00", "team1": "phoenix-suns", "team2": "los-angeles-clippers"}, {"date": "2014-04-02T22:00:00+04:00", "team1": "sacramento-kings", "team2": "los-angeles-lakers"}], [{"date": "2014-04-03T20:00:00+04:00", "team1": "oklahoma-city-thunder", "team2": "san-antonio-spurs"}, {"date": "2014-04-03T22:30:00+04:00", "team1": "los-angeles-clippers", "team2": "dallas-mavericks"}], [{"date": "2014-04-04T19:00:00+04:00", "team1": "memphis-grizzlies", "team2": "denver-nuggets"}, {"date": "2014-04-04T19:00:00+04:00", "team1": "charlotte-bobcats", "team2": "orlando_magic"}, {"date": "2014-04-04T19:00:00+04:00", "team1": "toronto-raptors", "team2": "indiana-pacers"}, {"date": "2014-04-04T19:30:00+04:00", "team1": "new-york-knicks", "team2": "washington-wizards"}, {"date": "2014-04-04T19:30:00+04:00", "team1": "brooklyn-nets", "team2": "detroit-pistons"}, {"date": "2014-04-04T19:30:00+04:00", "team1": "atlanta-hawks", "team2": "cleveland-cavaliers"}, {"date": "2014-04-04T19:30:00+04:00", "team1": "miami-heat", "team2": "minnesota-timberwolves"}, {"date": "2014-04-04T19:30:00+04:00", "team1": "boston-celtics", "team2": "philadelphia-76ers"}, {"date": "2014-04-04T20:00:00+04:00", "team1": "chicago-bulls", "team2": "milwaukee-bucks"}, {"date": "2014-04-04T21:00:00+04:00", "team1": "utah-jazz", "team2": "new-orleans-pelicans"}, {"date": "2014-04-04T21:30:00+04:00", "team1": "houston-rockets", "team2": "oklahoma-city-thunder"}, {"date": "2014-04-04T22:00:00+04:00", "team1": "portland-trail-blazers", "team2": "phoenix-suns"}, {"date": "2014-04-04T22:30:00+04:00", "team1": "los-angeles-lakers", "team2": "dallas-mavericks"}, {"date": "2014-04-04T22:30:00+04:00", "team1": "golden-state-warriors", "team2": "sacramento-kings"}], [{"date": "2014-04-05T19:00:00+04:00", "team1": "orlando_magic", "team2": "minnesota-timberwolves"}, {"date": "2014-04-05T19:00:00+04:00", "team1": "washington-wizards", "team2": "chicago-bulls"}, {"date": "2014-04-05T19:30:00+04:00", "team1": "philadelphia-76ers", "team2": "brooklyn-nets"}, {"date": "2014-04-05T19:30:00+04:00", "team1": "cleveland-cavaliers", "team2": "charlotte-bobcats"}, {"date": "2014-04-05T19:30:00+04:00", "team1": "detroit-pistons", "team2": "boston-celtics"}, {"date": "2014-04-05T20:30:00+04:00", "team1": "milwaukee-bucks", "team2": "toronto-raptors"}], [{"date": "2014-04-06T13:00:00+04:00", "team1": "miami-heat", "team2": "new-york-knicks"}, {"date": "2014-04-06T15:30:00+04:00", "team1": "los-angeles-clippers", "team2": "los-angeles-lakers"}, {"date": "2014-04-06T18:00:00+04:00", "team1": "sacramento-kings", "team2": "dallas-mavericks"}, {"date": "2014-04-06T18:00:00+04:00", "team1": "indiana-pacers", "team2": "atlanta-hawks"}, {"date": "2014-04-06T19:00:00+04:00", "team1": "san-antonio-spurs", "team2": "memphis-grizzlies"}, {"date": "2014-04-06T19:00:00+04:00", "team1": "houston-rockets", "team2": "denver-nuggets"}, {"date": "2014-04-06T21:00:00+04:00", "team1": "phoenix-suns", "team2": "oklahoma-city-thunder"}, {"date": "2014-04-06T21:00:00+04:00", "team1": "golden-state-warriors", "team2": "utah-jazz"}, {"date": "2014-04-06T21:00:00+04:00", "team1": "portland-trail-blazers", "team2": "new-orleans-pelicans"}], [{"date": "2014-04-08T20:00:00+04:00", "team1": "miami-heat", "team2": "brooklyn-nets"}, {"date": "2014-04-08T21:00:00+04:00", "team1": "utah-jazz", "team2": "dallas-mavericks"}, {"date": "2014-04-08T22:00:00+04:00", "team1": "sacramento-kings", "team2": "oklahoma-city-thunder"}, {"date": "2014-04-08T22:30:00+04:00", "team1": "los-angeles-lakers", "team2": "houston-rockets"}], [{"date": "2014-04-09T19:00:00+04:00", "team1": "cleveland-cavaliers", "team2": "detroit-pistons"}, {"date": "2014-04-09T19:00:00+04:00", "team1": "toronto-raptors", "team2": "philadelphia-76ers"}, {"date": "2014-04-09T19:00:00+04:00", "team1": "orlando_magic", "team2": "brooklyn-nets"}, {"date": "2014-04-09T19:00:00+04:00", "team1": "washington-wizards", "team2": "charlotte-bobcats"}, {"date": "2014-04-09T19:30:00+04:00", "team1": "atlanta-hawks", "team2": "boston-celtics"}, {"date": "2014-04-09T20:00:00+04:00", "team1": "new-orleans-pelicans", "team2": "phoenix-suns"}, {"date": "2014-04-09T20:00:00+04:00", "team1": "memphis-grizzlies", "team2": "miami-heat"}, {"date": "2014-04-09T20:00:00+04:00", "team1": "milwaukee-bucks", "team2": "indiana-pacers"}, {"date": "2014-04-09T20:00:00+04:00", "team1": "minnesota-timberwolves", "team2": "chicago-bulls"}, {"date": "2014-04-09T21:00:00+04:00", "team1": "denver-nuggets", "team2": "houston-rockets"}, {"date": "2014-04-09T22:00:00+04:00", "team1": "portland-trail-blazers", "team2": "sacramento-kings"}, {"date": "2014-04-09T22:30:00+04:00", "team1": "los-angeles-clippers", "team2": "oklahoma-city-thunder"}], [{"date": "2014-04-10T20:00:00+04:00", "team1": "dallas-mavericks", "team2": "san-antonio-spurs"}, {"date": "2014-04-10T22:30:00+04:00", "team1": "golden-state-warriors", "team2": "denver-nuggets"}], [{"date": "2014-04-11T19:00:00+04:00", "team1": "orlando_magic", "team2": "washington-wizards"}, {"date": "2014-04-11T19:00:00+04:00", "team1": "toronto-raptors", "team2": "new-york-knicks"}, {"date": "2014-04-11T19:30:00+04:00", "team1": "brooklyn-nets", "team2": "atlanta-hawks"}, {"date": "2014-04-11T19:30:00+04:00", "team1": "miami-heat", "team2": "indiana-pacers"}, {"date": "2014-04-11T19:30:00+04:00", "team1": "boston-celtics", "team2": "charlotte-bobcats"}, {"date": "2014-04-11T20:00:00+04:00", "team1": "chicago-bulls", "team2": "detroit-pistons"}, {"date": "2014-04-11T20:00:00+04:00", "team1": "oklahoma-city-thunder", "team2": "new-orleans-pelicans"}, {"date": "2014-04-11T20:00:00+04:00", "team1": "memphis-grizzlies", "team2": "philadelphia-76ers"}, {"date": "2014-04-11T20:00:00+04:00", "team1": "minnesota-timberwolves", "team2": "houston-rockets"}, {"date": "2014-04-11T20:30:00+04:00", "team1": "milwaukee-bucks", "team2": "cleveland-cavaliers"}, {"date": "2014-04-11T20:30:00+04:00", "team1": "san-antonio-spurs", "team2": "phoenix-suns"}, {"date": "2014-04-11T21:00:00+04:00", "team1": "utah-jazz", "team2": "portland-trail-blazers"}, {"date": "2014-04-11T22:30:00+04:00", "team1": "los-angeles-lakers", "team2": "golden-state-warriors"}], [{"date": "2014-04-12T15:30:00+04:00", "team1": "los-angeles-clippers", "team2": "sacramento-kings"}, {"date": "2014-04-12T19:00:00+04:00", "team1": "washington-wizards", "team2": "milwaukee-bucks"}, {"date": "2014-04-12T19:00:00+04:00", "team1": "charlotte-bobcats", "team2": "philadelphia-76ers"}, {"date": "2014-04-12T19:30:00+04:00", "team1": "cleveland-cavaliers", "team2": "boston-celtics"}, {"date": "2014-04-12T19:30:00+04:00", "team1": "atlanta-hawks", "team2": "miami-heat"}, {"date": "2014-04-12T20:00:00+04:00", "team1": "houston-rockets", "team2": "new-orleans-pelicans"}, {"date": "2014-04-12T20:30:00+04:00", "team1": "dallas-mavericks", "team2": "phoenix-suns"}, {"date": "2014-04-12T21:00:00+04:00", "team1": "denver-nuggets", "team2": "utah-jazz"}], [{"date": "2014-04-13T13:00:00+04:00", "team1": "new-york-knicks", "team2": "chicago-bulls"}, {"date": "2014-04-13T15:30:00+04:00", "team1": "detroit-pistons", "team2": "toronto-raptors"}, {"date": "2014-04-13T18:00:00+04:00", "team1": "brooklyn-nets", "team2": "orlando_magic"}, {"date": "2014-04-13T18:00:00+04:00", "team1": "indiana-pacers", "team2": "oklahoma-city-thunder"}, {"date": "2014-04-13T21:00:00+04:00", "team1": "portland-trail-blazers", "team2": "golden-state-warriors"}, {"date": "2014-04-13T21:00:00+04:00", "team1": "sacramento-kings", "team2": "minnesota-timberwolves"}, {"date": "2014-04-13T21:30:00+04:00", "team1": "los-angeles-lakers", "team2": "memphis-grizzlies"}], [{"date": "2014-04-14T19:00:00+04:00", "team1": "toronto-raptors", "team2": "milwaukee-bucks"}, {"date": "2014-04-14T19:00:00+04:00", "team1": "washington-wizards", "team2": "miami-heat"}, {"date": "2014-04-14T19:00:00+04:00", "team1": "philadelphia-76ers", "team2": "boston-celtics"}, {"date": "2014-04-14T19:30:00+04:00", "team1": "atlanta-hawks", "team2": "charlotte-bobcats"}, {"date": "2014-04-14T20:00:00+04:00", "team1": "chicago-bulls", "team2": "orlando_magic"}, {"date": "2014-04-14T20:00:00+04:00", "team1": "houston-rockets", "team2": "san-antonio-spurs"}, {"date": "2014-04-14T20:00:00+04:00", "team1": "new-orleans-pelicans", "team2": "oklahoma-city-thunder"}, {"date": "2014-04-14T21:00:00+04:00", "team1": "utah-jazz", "team2": "los-angeles-lakers"}, {"date": "2014-04-14T22:00:00+04:00", "team1": "phoenix-suns", "team2": "memphis-grizzlies"}, {"date": "2014-04-14T22:30:00+04:00", "team1": "golden-state-warriors", "team2": "minnesota-timberwolves"}], [{"date": "2014-04-15T20:00:00+04:00", "team1": "brooklyn-nets", "team2": "new-york-knicks"}, {"date": "2014-04-15T22:30:00+04:00", "team1": "los-angeles-clippers", "team2": "denver-nuggets"}], [{"date": "2014-04-16T20:00:00+04:00", "team1": "miami-heat", "team2": "philadelphia-76ers"}, {"date": "2014-04-16T20:00:00+04:00", "team1": "cleveland-cavaliers", "team2": "brooklyn-nets"}, {"date": "2014-04-16T20:00:00+04:00", "team1": "minnesota-timberwolves", "team2": "utah-jazz"}, {"date": "2014-04-16T20:00:00+04:00", "team1": "oklahoma-city-thunder", "team2": "detroit-pistons"}, {"date": "2014-04-16T20:00:00+04:00", "team1": "new-york-knicks", "team2": "toronto-raptors"}, {"date": "2014-04-16T20:00:00+04:00", "team1": "boston-celtics", "team2": "washington-wizards"}, {"date": "2014-04-16T20:00:00+04:00", "team1": "new-orleans-pelicans", "team2": "houston-rockets"}, {"date": "2014-04-16T20:00:00+04:00", "team1": "milwaukee-bucks", "team2": "atlanta-hawks"}, {"date": "2014-04-16T20:00:00+04:00", "team1": "san-antonio-spurs", "team2": "los-angeles-lakers"}, {"date": "2014-04-16T20:00:00+04:00", "team1": "orlando_magic", "team2": "indiana-pacers"}, {"date": "2014-04-16T20:00:00+04:00", "team1": "memphis-grizzlies", "team2": "dallas-mavericks"}, {"date": "2014-04-16T20:00:00+04:00", "team1": "charlotte-bobcats", "team2": "chicago-bulls"}, {"date": "2014-04-16T22:30:00+04:00", "team1": "portland-trail-blazers", "team2": "los-angeles-clippers"}, {"date": "2014-04-16T22:30:00+04:00", "team1": "denver-nuggets", "team2": "golden-state-warriors"}, {"date": "2014-04-16T22:30:00+04:00", "team1": "sacramento-kings", "team2": "phoenix-suns"}]]